wemake_python_styleguide/__init__.py
wemake_python_styleguide/checker.py
wemake_python_styleguide/cli/__init__.py
wemake_python_styleguide/cli/cli_app.py
wemake_python_styleguide/cli/commands/__init__.py
wemake_python_styleguide/cli/commands/base.py
wemake_python_styleguide/cli/commands/explain/__init__.py
wemake_python_styleguide/cli/commands/explain/command.py
wemake_python_styleguide/cli/commands/explain/message_formatter.py
wemake_python_styleguide/cli/commands/explain/module_loader.py
wemake_python_styleguide/cli/commands/explain/violation_loader.py
wemake_python_styleguide/cli/output.py
wemake_python_styleguide/compat/__init__.py
wemake_python_styleguide/compat/aliases.py
wemake_python_styleguide/compat/constants.py
wemake_python_styleguide/compat/functions.py
wemake_python_styleguide/compat/nodes.py
wemake_python_styleguide/compat/packaging.py
wemake_python_styleguide/compat/routing.py
wemake_python_styleguide/compat/types.py
wemake_python_styleguide/constants.py
wemake_python_styleguide/formatter.py
wemake_python_styleguide/logic/__init__.py
wemake_python_styleguide/logic/arguments/__init__.py
wemake_python_styleguide/logic/arguments/call_args.py
wemake_python_styleguide/logic/arguments/function_args.py
wemake_python_styleguide/logic/arguments/special_args.py
wemake_python_styleguide/logic/arguments/super_args.py
wemake_python_styleguide/logic/complexity/__init__.py
wemake_python_styleguide/logic/complexity/annotations.py
wemake_python_styleguide/logic/complexity/cognitive.py
wemake_python_styleguide/logic/complexity/functions.py
wemake_python_styleguide/logic/complexity/overuses.py
wemake_python_styleguide/logic/filenames.py
wemake_python_styleguide/logic/naming/__init__.py
wemake_python_styleguide/logic/naming/access.py
wemake_python_styleguide/logic/naming/alphabet.py
wemake_python_styleguide/logic/naming/blacklists.py
wemake_python_styleguide/logic/naming/builtins.py
wemake_python_styleguide/logic/naming/constants.py
wemake_python_styleguide-1.5.0.dist-info/METADATA
wemake_python_styleguide-1.5.0.dist-info/WHEEL
wemake_python_styleguide-1.5.0.dist-info/entry_points.txt
wemake_python_styleguide-1.5.0.dist-info/licenses/LICENSE
wemake_python_styleguide-1.5.0.dist-info/RECORD
